LICENSE
MANIFEST.in
README.md
requirements.txt
setup.cfg
setup.py
addanase/__init__.py
addanase/__main__.py
addanase/common.py
addanase/drawer.py
addanase/exceptions.py
addanase/structures.py
addanase.egg-info/PKG-INFO
addanase.egg-info/SOURCES.txt
addanase.egg-info/dependency_links.txt
addanase.egg-info/not-zip-safe
addanase.egg-info/requires.txt
addanase.egg-info/top_level.txt
tests/test_addanase.py
tests/test_area.py
tests/test_base.py
tests/test_city.py
tests/test_cut.py
tests/test_pcaconcat.py
tests/test_province.py
tests/test_structures.py