Metadata-Version: 2.1
Name: addanase
Version: 0.0.1
Summary: address analysis
Home-page: https://github.com/advancehs/addanase
Author: advancehs
Author-email: 1019753743@qq.com
License: MIT license
Keywords: addanase
Classifier: Intended Audience :: Developers
Classifier: License :: OSI Approved :: MIT License
Classifier: Natural Language :: English
Classifier: Programming Language :: Python :: 3
Classifier: Programming Language :: Python :: 3.8
Classifier: Programming Language :: Python :: 3.9
Classifier: Programming Language :: Python :: 3.10
Classifier: Programming Language :: Python :: 3.11
Requires-Python: >=3.8
License-File: LICENSE
